replgpt/__init__.py
replgpt/__main__.py
replgpt/prompt_or_code.py
replgpt/replgpt.py
tests/__init__.py
tests/test_is_code_check.py
tests/test_prompt_or_code.py
tests/test_replgpt.py
replgpt-0.1.1.dist-info/METADATA
replgpt-0.1.1.dist-info/WHEEL
replgpt-0.1.1.dist-info/entry_points.txt
replgpt-0.1.1.dist-info/top_level.txt
replgpt-0.1.1.dist-info/RECORD
