Metadata-Version: 2.1
Name: replgpt
Version: 0.1.1
Summary: An interactive REPL with GPT-based assistance
Home-page: https://github.com/yourusername/replgpt
Author: Your Name
Author-email: your.email@example.com
License: UNKNOWN
Platform: UNKNOWN
Classifier: Programming Language :: Python :: 3
Classifier: License :: OSI Approved :: BSD License
Classifier: Operating System :: OS Independent
Requires-Python: >=3.6
Requires-Dist: openai<1.0.0,>=0.27.4
